ltaoist/__init__.py
ltaoist/beta_machine/BetaMachine.py
ltaoist/beta_machine/__init__.py
ltaoist/ltaoist/__init__.py
ltaoist/ltaoist/ltaoist.py
ltaoist/plane_calculation/PlaneSet.py
ltaoist/plane_calculation/__init__.py
ltaoist/plane_calculation/test.py
python_ltaoist-0.4.dist-info/DESCRIPTION.rst
python_ltaoist-0.4.dist-info/METADATA
python_ltaoist-0.4.dist-info/RECORD
python_ltaoist-0.4.dist-info/WHEEL
python_ltaoist-0.4.dist-info/metadata.json
python_ltaoist-0.4.dist-info/top_level.txt
