Metadata-Version: 2.0
Name: python-ltaoist
Version: 0.4
Summary: Let import ltaoist and from ltaoist import start
Home-page: http://github.com/dist1/python-ltaoist
Author: ltaoit
Author-email: ltaoist6@gmail.com
License: GPLv3
Platform: UNKNOWN
